generated/example.v
module example(
  input        clock,
  input        reset,
  input  [3:0] io_a, // @[src/main/scala/Comb/operator.scala 60:14]
  input  [3:0] io_b, // @[src/main/scala/Comb/operator.scala 60:14]
  output [7:0] io_o // @[src/main/scala/Comb/operator.scala 60:14]
);
  assign io_o = $signed(io_a) * $signed(io_b); // @[src/main/scala/Comb/operator.scala 66:16]
endmodule

test_run_dir/operatorTest_should_pass/example.vcd
$date
2025-12-18T05:35+0000
$end
$version
0.2
$end
$comment

$end
$timescale 1ns  $end
$scope module example $end
 $var wire 8 ! io_o $end
 $var wire 4 " io_b $end
 $var wire 4 # io_a $end
 $var wire 1 $ reset $end
 $var wire 1 % clock $end
$upscope $end
$enddefinitions $end
$dumpvars
b0000 "
b0000 #
0$
0%
b00000000 !
$end
#0
1$
#1
1%
#6
0$
0%
#11
1%
#16
b11111010 !
b0011 "
b1110 #
0%
#21
1%
#26
b00011100 !
b0111 "
b0100 #
0%
#31
1%
#36
b00011110 !
b1011 "
b1010 #
0%
#41
1%
#46
b11111010 !
b1101 "
b0010 #
0%
#51
1%
#56
b00110001 !
b0111 "
b0111 #
0%
#61
1%
#66
b01000000 !
b1000 "
b1000 #
0%
#71
1%
#76
0%
#81
1%
#86
0%
#91
1%
#96
0%
#101
1%
#106
0%
#111
1%
#116
b0000 "
b0000 #
0%
